<annotation>
	<folder>Exact</folder>
	<filename>vests340.jpg</filename>
	<path>C:\Users\nidhi.singh\PPE\Exact\vests340.jpg</path>
	<source>
		<database>Unknown</database>
	</source>
	<size>
		<width>270</width>
		<height>186</height>
		<depth>3</depth>
	</size>
	<segmented>0</segmented>
	<object>
		<name>helmet</name>
		<pose>Unspecified</pose>
		<truncated>0</truncated>
		<difficult>0</difficult>
		<bndbox>
			<xmin>18</xmin>
			<ymin>4</ymin>
			<xmax>149</xmax>
			<ymax>73</ymax>
		</bndbox>
	</object>
</annotation>
